fast_causal_shap/__init__.py
fast_causal_shap/core.py
fast_causal_shap-0.3.0.dist-info/licenses/LICENSE
fast_causal_shap-0.3.0.dist-info/METADATA
fast_causal_shap-0.3.0.dist-info/WHEEL
fast_causal_shap-0.3.0.dist-info/top_level.txt
fast_causal_shap-0.3.0.dist-info/RECORD
