Metadata-Version: 2.4
Name: fast-causal-shap
Version: 0.3.0
Summary: A Python package for efficient causal SHAP computations
Author-email: woonyee28 <ngnwy289@gmail.com>
License: MIT
Project-URL: Homepage, https://github.com/woonyee28/CausalSHAP
Project-URL: Issues, https://github.com/woonyee28/CausalSHAP/issues
Requires-Python: >=3.9
License-File: LICENSE
Requires-Dist: pandas>=1.0.0
Requires-Dist: networkx>=2.0
Requires-Dist: numpy>=1.18.0
Requires-Dist: scikit-learn>=0.24.0
Provides-Extra: dev
Requires-Dist: pytest>=6.0; extra == "dev"
Requires-Dist: black>=21.0; extra == "dev"
Requires-Dist: flake8>=3.8; extra == "dev"
Requires-Dist: mypy>=0.800; extra == "dev"
Requires-Dist: isort>=5.0; extra == "dev"
Requires-Dist: pytest-cov>=2.0; extra == "dev"
Requires-Dist: pre-commit>=2.0; extra == "dev"
Requires-Dist: mkdocs>=1.5.0; extra == "dev"
Requires-Dist: mkdocs-material>=9.0.0; extra == "dev"
Requires-Dist: mkdocstrings[python]>=0.24.0; extra == "dev"
Requires-Dist: mkdocs-autorefs>=0.5.0; extra == "dev"
Dynamic: license-file
